temppythonsample/__init__.py
temppythonsample/authService.py
temppythonsample/makana.py
temppythonsample/models.py
temppythonsample/temp.py
temppythonsample/test.py
temppythonsample-0.3.1.dist-info/LICENSE.txt
temppythonsample-0.3.1.dist-info/METADATA
temppythonsample-0.3.1.dist-info/WHEEL
temppythonsample-0.3.1.dist-info/top_level.txt
temppythonsample-0.3.1.dist-info/RECORD
