Metadata-Version: 2.1
Name: temppythonsample
Version: 0.3.1
Summary: First Python Library
Home-page: UNKNOWN
Author: AlpsInfoITSolution
Author-email: yash.patel@alpsinfo.net
License: UNKNOWN
Keywords: Makana Python Library
Platform: UNKNOWN
Classifier: Development Status :: 3 - Alpha
Classifier: Intended Audience :: Developers
Classifier: Topic :: Software Development :: Build Tools
Classifier: License :: OSI Approved :: MIT License
Classifier: Programming Language :: Python
Classifier: Programming Language :: Python :: 3
Classifier: Programming Language :: Python :: 3.7
Classifier: Programming Language :: Python :: 3.8
Classifier: Programming Language :: Python :: 3.9
Classifier: Programming Language :: Python :: 3.10
Requires-Python: ~=3.6
License-File: LICENSE.txt
